splines/__init__.py
splines/quaternion.py
splines-0.3.3.dist-info/licenses/LICENSE
splines-0.3.3.dist-info/METADATA
splines-0.3.3.dist-info/WHEEL
splines-0.3.3.dist-info/top_level.txt
splines-0.3.3.dist-info/zip-safe
splines-0.3.3.dist-info/RECORD
