Metadata-Version: 2.4
Name: splines
Version: 0.3.3
Summary: Splines in Euclidean Space and Beyond
Home-page: https://splines.readthedocs.io/
Author: Matthias Geier
Author-email: Matthias.Geier@gmail.com
License: MIT
Project-URL: Documentation, https://splines.readthedocs.io/
Project-URL: Source Code, https://github.com/AudioSceneDescriptionFormat/splines/
Project-URL: Bug Tracker, https://github.com/AudioSceneDescriptionFormat/splines/issues/
Keywords: splines,curves,interpolation,quaternions
Platform: any
Classifier: Intended Audience :: Education
Classifier: Intended Audience :: Science/Research
Classifier: License :: OSI Approved :: MIT License
Classifier: Operating System :: OS Independent
Classifier: Programming Language :: Python
Classifier: Programming Language :: Python :: 3
Requires-Python: >=3.7
License-File: LICENSE
Requires-Dist: NumPy
Dynamic: author
Dynamic: author-email
Dynamic: classifier
Dynamic: description
Dynamic: home-page
Dynamic: keywords
Dynamic: license
Dynamic: license-file
Dynamic: platform
Dynamic: project-url
Dynamic: requires-dist
Dynamic: requires-python
Dynamic: summary
